langchain_jieba/__init__.py
langchain_jieba/graph_vectorstores/extractors/jieba_link_extractor.py
langchain_jieba-0.1.1.dist-info/LICENSE
langchain_jieba-0.1.1.dist-info/METADATA
langchain_jieba-0.1.1.dist-info/WHEEL
langchain_jieba-0.1.1.dist-info/RECORD
